random_phone/RandomUkPhone.py
random_phone/__init__.py
RandomPhone-0.0.1.dist-info/LICENSE
RandomPhone-0.0.1.dist-info/METADATA
RandomPhone-0.0.1.dist-info/WHEEL
RandomPhone-0.0.1.dist-info/top_level.txt
RandomPhone-0.0.1.dist-info/RECORD
