Metadata-Version: 2.1
Name: RandomPhone
Version: 0.0.1
Summary: A module to generate random phone numbers
Home-page: https://github.com/rfranks-securenet/RandomPhone
Author: Richard Franks
Author-email: richard.franks@securenetcoms.co.uk
License: LICENSE
Platform: UNKNOWN
Classifier: Intended Audience :: Developers
Classifier: License :: OSI Approved :: MIT License
Classifier: Programming Language :: Python
Classifier: Natural Language :: English
Classifier: Development Status :: 5 - Production/Stable
Classifier: Programming Language :: Python :: 2.7
Classifier: Programming Language :: Python :: 3.4
Classifier: Programming Language :: Python :: 3.5
Classifier: Programming Language :: Python :: 3.6
Classifier: Programming Language :: Python :: 3.7
Classifier: Programming Language :: Python :: 3.8
Classifier: Topic :: Software Development :: Libraries :: Python Modules
Provides-Extra: testing
Requires-Dist: pytest ; extra == 'testing'
